algorhythms/__init__.py
algorhythms/sort.py
algorhythms/string_matching.py
algorhythms-0.0.2.2.dist-info/LICENSE
algorhythms-0.0.2.2.dist-info/METADATA
algorhythms-0.0.2.2.dist-info/WHEEL
algorhythms-0.0.2.2.dist-info/top_level.txt
algorhythms-0.0.2.2.dist-info/RECORD
