Metadata-Version: 2.1
Name: algorhythms
Version: 0.0.2.2
Summary: algorhythms
Home-page: https://github.com/RishabhBhatnagar/algorhythms
Author: Rishabh Bhatnagar
Author-email: bhatnagarrishabh4@gmail.com
License: UNKNOWN
Platform: UNKNOWN
Classifier: Programming Language :: Python :: 3
Classifier: License :: OSI Approved :: MIT License
Classifier: Operating System :: OS Independent
